fcompdata/__init__.py
fcompdata/download.py
fcompdata/fcompdata.py
fcompdata/py.typed
fcompdata/data/__init__.py
fcompdata/data/m1_data.json
fcompdata/data/m3_data.json
fcompdata/data/tcomp_data.json
fcompdata-0.1.1.dist-info/METADATA
fcompdata-0.1.1.dist-info/WHEEL
fcompdata-0.1.1.dist-info/licenses/LICENSE
fcompdata-0.1.1.dist-info/RECORD
