Metadata-Version: 2.4
Name: fcompdata
Version: 0.1.1
Summary: Forecasting Competitions Datasets (M1, M3, Tourism) for Python
Project-URL: Homepage, https://github.com/config-i1/fcompdata
Project-URL: Repository, https://github.com/config-i1/fcompdata
Author-email: Ivan Svetunkov <ivan@svetunkov.com>
License-Expression: LGPL-3.0-or-later
License-File: LICENSE
Keywords: datasets,forecasting,m-competition,time-series
Classifier: Development Status :: 4 - Beta
Classifier: Intended Audience :: Science/Research
Classifier: License :: OSI Approved :: GNU Lesser General Public License v3 or later (LGPLv3+)
Classifier: Operating System :: OS Independent
Classifier: Programming Language :: Python :: 3
Classifier: Programming Language :: Python :: 3.10
Classifier: Programming Language :: Python :: 3.11
Classifier: Programming Language :: Python :: 3.12
Classifier: Programming Language :: Python :: 3.13
Classifier: Topic :: Scientific/Engineering
Requires-Python: >=3.10
Requires-Dist: numpy>=1.20
Provides-Extra: dev
Requires-Dist: mypy>=1.0; extra == 'dev'
Requires-Dist: pytest-cov>=4.0; extra == 'dev'
Requires-Dist: pytest>=7.0; extra == 'dev'
Requires-Dist: ruff>=0.1.0; extra == 'dev'
